django_trusted_devices-1.3.dist-info/licenses/LICENSE
trusted_devices/__init__.py
trusted_devices/admin.py
trusted_devices/apps.py
trusted_devices/authentication.py
trusted_devices/models.py
trusted_devices/permissions.py
trusted_devices/schema.py
trusted_devices/serializers.py
trusted_devices/settings.py
trusted_devices/signals.py
trusted_devices/tests.py
trusted_devices/tokens.py
trusted_devices/urls.py
trusted_devices/utils.py
trusted_devices/views.py
trusted_devices/migrations/0001_initial.py
trusted_devices/migrations/__init__.py
django_trusted_devices-1.3.dist-info/METADATA
django_trusted_devices-1.3.dist-info/WHEEL
django_trusted_devices-1.3.dist-info/top_level.txt
django_trusted_devices-1.3.dist-info/RECORD
