Metadata-Version: 2.4
Name: django-trusted-devices
Version: 1.3
Summary: Secure and manage trusted login devices for Django users
Author-email: Jakhongir Ganiev <contact@jakhongir.dev>
License: MIT
Keywords: django,trusted devices,user security,sessions,login,djangorestframework
Classifier: Development Status :: 3 - Alpha
Classifier: Framework :: Django
Classifier: Framework :: Django :: 4.2
Classifier: Framework :: Django :: 5.0
Classifier: Framework :: Django :: 5.1
Classifier: Framework :: Django :: 5.2
Classifier: Intended Audience :: Developers
Classifier: License :: OSI Approved :: MIT License
Classifier: Programming Language :: Python :: 3.10
Classifier: Programming Language :: Python :: 3.11
Classifier: Programming Language :: Python :: 3.12
Requires-Python: >=3.10
License-File: LICENSE
Requires-Dist: django<5.3,>=4.2
Requires-Dist: djangorestframework>=3.14.0
Requires-Dist: djangorestframework-simplejwt>=5.5.0
Requires-Dist: drf-spectacular>=0.28.0
Requires-Dist: httpx>=0.28.1
Provides-Extra: docs
Requires-Dist: mkdocs; extra == "docs"
Requires-Dist: mkdocs-material; extra == "docs"
Provides-Extra: dev
Requires-Dist: black>=25.1.0; extra == "dev"
Requires-Dist: build>=1.2.2.post1; extra == "dev"
Requires-Dist: flake8>=7.2.0; extra == "dev"
Requires-Dist: isort>=6.0.1; extra == "dev"
Requires-Dist: pytest>=8.3.5; extra == "dev"
Requires-Dist: pytest-cov>=6.1.1; extra == "dev"
Requires-Dist: pytest-django>=4.11.1; extra == "dev"
Requires-Dist: twine>=6.1.0; extra == "dev"
Dynamic: license-file
